orbital/__init__.py
orbitalmaterials-0.1.dist-info/LICENSE
orbitalmaterials-0.1.dist-info/METADATA
orbitalmaterials-0.1.dist-info/WHEEL
orbitalmaterials-0.1.dist-info/top_level.txt
orbitalmaterials-0.1.dist-info/RECORD
