Metadata-Version: 2.1
Name: orbitalmaterials
Version: 0.1
Summary: Foundation models for computational chemistry.
Author: Orbital Materials
License: Apache-2.0
Project-URL: Homepage, https://github.com/orbital-materials/orbitalmaterials
Project-URL: Changelog, https://github.com/orbital-materials/orbitalmaterials/releases
Project-URL: Issues, https://github.com/orbital-materials/orbitalmaterials/issues
Project-URL: CI, https://github.com/orbital-materials/orbitalmaterials/actions
Classifier: License :: OSI Approved :: Apache Software License
Requires-Python: >=3.8
License-File: LICENSE
Provides-Extra: test
Requires-Dist: pytest ; extra == 'test'
